LICENSE
README.rst
setup.cfg
setup.py
accounts/__init__.py
accounts/admin.py
accounts/apps.py
accounts/forms.py
accounts/models.py
accounts/tests.py
accounts/views.py
accounts/migrations/0001_initial.py
accounts/migrations/__init__.py
django_custom_acccounts_plus.egg-info/PKG-INFO
django_custom_acccounts_plus.egg-info/SOURCES.txt
django_custom_acccounts_plus.egg-info/dependency_links.txt
django_custom_acccounts_plus.egg-info/top_level.txt